langextract_openrouter/__init__.py
langextract_openrouter/provider.py
langextract_provider_openrouter-0.1.3.dist-info/METADATA
langextract_provider_openrouter-0.1.3.dist-info/WHEEL
langextract_provider_openrouter-0.1.3.dist-info/entry_points.txt
langextract_provider_openrouter-0.1.3.dist-info/top_level.txt
langextract_provider_openrouter-0.1.3.dist-info/RECORD
