Metadata-Version: 2.4
Name: langextract-provider-openrouter
Version: 0.1.3
Summary: LangExtract provider plugin for OpenRouter API
Author-email: Shneior Shprintsin <106022521+shprintsin@users.noreply.github.com>
License: Apache-2.0
Requires-Python: >=3.10
Requires-Dist: langextract>=1.0.0
Requires-Dist: requests
